django_menus/__init__.py
django_menus/apps.py
django_menus/includes.py
django_menus/menu/__init__.py
django_menus/menu/menu.py
django_menus/menu/menu_items.py
django_menus/menu/tabs.py
django_menus/static/django_menus/django_menus.css
django_menus/static/django_menus/django_menus.js
django_menus/templates/django_menus/ajax_tooltip.html
django_menus/templates/django_menus/breadcrumb.html
django_menus/templates/django_menus/button_group.html
django_menus/templates/django_menus/button_menu.html
django_menus/templates/django_menus/dropdown.html
django_menus/templates/django_menus/main_menu.html
django_menus/templates/django_menus/menu_key_press.html
django_menus/templates/django_menus/single_button.html
django_menus/templates/django_menus/tab_menu.html
django_menus/templatetags/__init__.py
django_menus/templatetags/django_menu_tags.py
django_tab_menus-0.0.17.dist-info/LICENSE
django_tab_menus-0.0.17.dist-info/METADATA
django_tab_menus-0.0.17.dist-info/WHEEL
django_tab_menus-0.0.17.dist-info/top_level.txt
django_tab_menus-0.0.17.dist-info/RECORD
