Metadata-Version: 2.1
Name: django-tab-menus
Version: 0.0.17
Summary: Django app to render menus and load tabs with Ajax
Home-page: https://github.com/jonesim/django-menus
Author: Ian Jones
Classifier: Programming Language :: Python :: 3
Classifier: License :: OSI Approved :: MIT License
Classifier: Operating System :: OS Independent
Requires-Python: >=3.6
License-File: LICENSE
Requires-Dist: django-ajax-helpers
